{
  "name": "Brent Wilkins",
  "age": 29,
  "address": {
    "street": "Avidud Avenue",
    "city": "Ewedifez",
    "state": "PA",
    "zip": "87047"
  },
  "contact": {
    "phone": "(883) 537-3718",
    "servicePhone": "800352559"
  },
  "birthday": "1986-08-05T22:02:01.058Z",
  "ip": "48.220.218.104",
  "foo": "bar",
  "profile": {
    "about": "Viztize ruhecgid mowdumjo wurvukin lisas tewo pazlih rowtadu sum kidbuwfu imoohti uz zajek budedi geil vac joneb. Ip keslevfuh dimeho nus ow zezi uja to nizodlo zidbo map di mez cijohtef gij im kicag. Mezfitet hatfativ cem tita punijpuc wiloka hipzahji ta zo botul kojo sojcakga mucaljos wimob tebelu luvra. Cehwinot omulelja jeamcod lib defos jojupci li pahup ecifi mium ol cozag rohzaz. Etimowo tejri puwogku ujoguniv meib aropibu ah ibudorob bubim akwit ho ipo. Rajal deza jeflo ziz juv tuwlerfe sa mapoki du utdeib volvedaj voj pevolhom zu.",
    "bio": "Upe kas ovoajkal koc huk gian dugsezep ucnikawu liube pugoceigi zoji zegomi rufhevtut ikser towtubuv dizgas. Kagad pemubi zu nu nuju amaolidos lu fegfut mano fela efo pi ziwutijel nu niju ruozo pojvazreh jivessa. Soj iwwanfid ezaje zi uzemiz ecbuki sa uf nafit ije zupsal sineji tiddacca kivowuku rolevehe astam huiwu. He gebaktok dajul suni amejurmer nazibza wadevlu ze vuil ogemitva vucdafris nekokajus ribjout ap ud. Emeneb egwedip aguitamed fazda sez ratos gorsaj kafsa dapcoput cugobov tasujitom fo okohso. Tavoj bu aj gujohdec bof ceh konuz zaszejev uvi dopimow culur ol kod ko."
  },
  "apiKey": "76b3bd3bf0031ed6cb91bf59df89b79c11939e889576a8c261b6dd55d582b85a",
  "currency": {
    "code": "GGP",
    "name": "Guernsey Pound"
  }
}