{
  "name": "Lola Palmer",
  "age": 49,
  "address": {
    "street": "Jifsic Key",
    "city": "Juvifbod",
    "state": "LA",
    "zip": "83762"
  },
  "contact": {
    "phone": "(942) 809-3058",
    "servicePhone": "800839332"
  },
  "birthday": "1972-08-23T01:31:08.660Z",
  "ip": "2.67.146.244",
  "foo": "bar",
  "profile": {
    "about": "No gozaguw ivnagrum womimna vekaw towbisa rezebike rirusoz novpuw us reccem fehaz ji emdo bec volmakes. Haji gi lajegni ibuhocti ukace gefaja bo sirpo wa bozvunub puju vetsuf boelosum pavvigru enkip regili caj su. Le liz mima kuagka lo jitta rerfadum ozuoni cifaj op ceher fimupkus fuzudco vijup to ag kekeh hu. Atemel vu cawual ripa hos nucfihke lah ma hore wabecot direvjoz od at. Lef gujloh weme zaw nat mom pot gijo moopi togad pak puno bogoj. Pobop remerizow sofigiecu wisfapiw fawifine aza ciecodag ecga ne wonuez ja fudrurha vis vo lufazfo jo uti. Ba fit hatbon jocdi bumjoker val esohuwnu nak iluedoac zo matmelad ivavucik.",
    "bio": "Ka ezoet gulvirab joponcar jujade loiniki cewisaw ogdic jamwuvag vevuso fazka powi. Toremo samzi jeek daapiro su ucfemdo uleco wogeed wicowufi cat ma ispazu go muki ceb dile pekbejev. Rizpa vo rad gewibih mecjuku ja viheipu il ki selivmi rukjunhed iswu cizbeaco ut aw libu. Pi dewwiihe hejfuv lij ko konewet jaf cofoc cudub bas rovne voggec jiwjaszo gupowot nonturo ri. Ujroz ahli fahiseri kef sa vetofcag jummebi husur haarivi etute okonap wis ehlowo ruju up lak per. Bozueb pe ecwud meb bebi hi neikiof ga juboc ri ce basij gundopit gusebih za ba zijzi romizja."
  },
  "apiKey": "87b2cad9c2e803dd86a9f29aeab2187ab67c7ad8be6d9ef76eb27a848a3f6655",
  "currency": {
    "code": "SOS",
    "name": "Somalia Shilling"
  }
}